biosynfoni/__init__.py
biosynfoni/cli.py
biosynfoni/concerto_fp.py
biosynfoni/fingerprints.py
biosynfoni/inoutput.py
biosynfoni/mol_highlights.py
biosynfoni/moldrawing.py
biosynfoni/rdkfnx.py
biosynfoni/subkeys/__init__.py
biosynfoni/subkeys/biosmartfonis.py
biosynfoni/subkeys/default_version.py
biosynfoni/subkeys/get_version.py
biosynfoni/subkeys/versionfonis.py
biosynfoni-1.0.0.dist-info/METADATA
biosynfoni-1.0.0.dist-info/WHEEL
biosynfoni-1.0.0.dist-info/entry_points.txt
biosynfoni-1.0.0.dist-info/licenses/LICENSE
biosynfoni-1.0.0.dist-info/RECORD
