Metadata-Version: 2.4
Name: biosynfoni
Version: 1.0.0
Summary: a *biosynformatic* fingerprint to explore natural product distance and diversity
Project-URL: homepage, https://github.com/lucinamay/biosynfoni
Author: Lucina-May Nollen
Maintainer: Lucina-May Nollen
License: MIT License
License-File: LICENSE
Keywords: bioinformatics,biosynthetic-distance,cheminformatics,metabolites,metabolomics,molecular-fingerprint,natural-products
Requires-Python: >=3.9
Requires-Dist: numpy
Requires-Dist: rdkit
Requires-Dist: tqdm
Provides-Extra: dev
Requires-Dist: black; extra == 'dev'
Requires-Dist: black[jupyter]; extra == 'dev'
Requires-Dist: pytest; extra == 'dev'
Provides-Extra: experiments
Requires-Dist: jupyter; extra == 'experiments'
Requires-Dist: matplotlib; extra == 'experiments'
Requires-Dist: networkx; extra == 'experiments'
Requires-Dist: pandas; extra == 'experiments'
Requires-Dist: requests; extra == 'experiments'
Requires-Dist: scikit-learn>=1.3.0; extra == 'experiments'
Requires-Dist: scipy; extra == 'experiments'
Requires-Dist: seaborn; extra == 'experiments'
Requires-Dist: umap-learn; extra == 'experiments'
Provides-Extra: test
Requires-Dist: matplotlib; extra == 'test'
